fastiv/__init__.py
fastiv/constant.py
fastiv/iv.py
fastiv/parser.py
FastIV-0.1.dist-info/LICENSE
FastIV-0.1.dist-info/METADATA
FastIV-0.1.dist-info/WHEEL
FastIV-0.1.dist-info/top_level.txt
FastIV-0.1.dist-info/RECORD
