Metadata-Version: 2.1
Name: FastIV
Version: 0.1
Summary: A package to compute weight of evidence (WOE) and Information Value (IV) easily, with cross-features supported
Home-page: https://github.com/chinapnr/FastIV.git
Author: miaotianshi
Author-email: miaotianshi@126.com
License: UNKNOWN
Platform: UNKNOWN
Classifier: Programming Language :: Python :: 3
Classifier: License :: OSI Approved :: MIT License
Classifier: Operating System :: OS Independent
Requires-Dist: scikit-learn (>=0.20.3)
Requires-Dist: pandas (>=0.25.1)
Requires-Dist: numpy (>=1.16.2)
